{
  "Header": {
    "title": "we are Avenir Trading",
    "paragraph": "Welcome to Avenir Trading , discover excellence at the heart of everything we do."
  },
  "About": {
    "paragraph": "At Avenir Trading, we are dedicated to delivering exceptional solutions that transform ideas into reality. With a team of passionate experts, we strive to exceed expectations and build lasting relationships. Our mission is to bring innovation, quality, and reliability to every project we undertake.",
    "Why": [
      "Unmatched Quality Standards",
      "Global Reach",
      "Sustainability Commitment",
      "Trusted Expertise"
    ],
    "Why2": [
      "Customer-Centric Approach",
      "Wide Range of Products",
      "Timely Delivery",
      "Strong Industry Relationships"
    ]
  },
  "Gallery": [
    {
      "title": "agri-food",
      "largeImage": "img/portfolio/01-large.jpg",
      "smallImage": "img/portfolio/01-small.jpg"
    },
    {
      "title": "agronomy",
      "largeImage": "img/portfolio/02-large.jpg",
      "smallImage": "img/portfolio/02-small.jpg"
    },
    {
      "title": "Project Title",
      "largeImage": "img/portfolio/03-large.jpg",
      "smallImage": "img/portfolio/03-small.jpg"
    },
    {
      "title": "Project Title",
      "largeImage": "img/portfolio/04-large.jpg",
      "smallImage": "img/portfolio/04-small.jpg"
    },
    {
      "title": "Project Title",
      "largeImage": "img/portfolio/05-large.jpg",
      "smallImage": "img/portfolio/05-small.jpg"
    },
    {
      "title": "Project Title",
      "largeImage": "img/portfolio/06-large.jpg",
      "smallImage": "img/portfolio/06-small.jpg"
    },
    {
      "title": "Project Title",
      "largeImage": "img/portfolio/07-large.jpg",
      "smallImage": "img/portfolio/07-small.jpg"
    },
    {
      "title": "Project Title",
      "largeImage": "img/portfolio/08-large.jpg",
      "smallImage": "img/portfolio/08-small.jpg"
    },
    {
      "title": "Project Title",
      "largeImage": "img/portfolio/09-large.jpg",
      "smallImage": "img/portfolio/09-small.jpg"
    }
  ],
  "Services": [
    {
      "icon": "fa fa-briefcase",
      "name": "Premium Product Export",
      "text": "We ensure that the finest Algerian fruits and vegetables reach global markets with unparalleled quality and freshness."
    },
    {
      "icon": "fa fa-cart-arrow-down",
      "name": "Logistics and Transportation",
      "text": "Seamless logistics services, guaranteeing timely and safe delivery of goods worldwide."
    },
    {
      "icon": "fa fa-cloud-download",
      "name": "Market Consultancy",
      "text": "Gain a competitive edge with tailored market insights and strategies, ensuring optimal growth and seamless entry into international markets."
    },
    {
      "icon": "fa fa-language",
      "name": "Customs Clearance Assistance",
      "text": "Professional support for smooth customs clearance and regulatory compliance."
    },
    {
      "icon": "fa fa-plane",
      "name": "Supply Chain Management",
      "text": "End-to-end supply chain solutions tailored to your business needs."
    },
    {
      "icon": "fa fa-pie-chart",
      "name": "Product Sourcing",
      "text": "Leveraging our network to source and deliver the highest quality products."
    }
  ],
  "Testimonials": [
    {
      "img": "img/testimonials/01.jpg",
      "text": "\"Lorem ipsum dolor sit amet, consectetur adipiscing elit. Duis sed dapibus leo nec ornare diam sedasd commodo nibh ante facilisis bibendum dolor feugiat at.\"",
      "name": "John Doe"
    },
    {
      "img": "img/testimonials/02.jpg",
      "text": "\"Lorem ipsum dolor sit amet, consectetur adipiscing elit. Duis sed dapibus leo nec ornare diam sedasd commodo nibh ante facilisis bibendum dolor feugiat at.\"",
      "name": "Johnathan Doe"
    },
    {
      "img": "img/testimonials/03.jpg",
      "text": "\"Lorem ipsum dolor sit amet, consectetur adipiscing elit. Duis sed dapibus leo nec ornare diam sedasd commodo nibh ante facilisis bibendum dolor feugiat at.\"",
      "name": "John Doe"
    },
    {
      "img": "img/testimonials/04.jpg",
      "text": "\"Lorem ipsum dolor sit amet, consectetur adipiscing elit. Duis sed dapibus leo nec ornare diam sedasd commodo nibh ante facilisis bibendum dolor feugiat at.\"",
      "name": "Johnathan Doe"
    },
    {
      "img": "img/testimonials/05.jpg",
      "text": "\"Lorem ipsum dolor sit amet, consectetur adipiscing elit. Duis sed dapibus leo nec ornare diam sedasd commodo nibh ante facilisis bibendum dolor feugiat at.\"",
      "name": "John Doe"
    },
    {
      "img": "img/testimonials/06.jpg",
      "text": "\"Lorem ipsum dolor sit amet, consectetur adipiscing elit. Duis sed dapibus leo nec ornare diam sedasd commodo nibh ante facilisis bibendum dolor feugiat at.\"",
      "name": "Johnathan Doe"
    }
  ],
  "Team": [
    {
      "img": "img/team/01.jpg",
      "name": "John Doe",
      "job": "Director"
    },
    {
      "img": "img/team/02.jpg",
      "name": "Mike Doe",
      "job": "Senior Designer"
    },
    {
      "img": "img/team/03.jpg",
      "name": "Jane Doe",
      "job": "Senior Designer"
    },
    {
      "img": "img/team/04.jpg",
      "name": "Karen Doe",
      "job": "Project Manager"
    }
  ],
  "Contact": {
    "address": "Résidence yasmine lot 09-N°7 beni mered ; Blida - Algeria ",
    "phone": "+213 556 30 84 71",
    "email": "info@avenir-trading.com",
    "facebook": "fb.com",
    "twitter": "twitter.com",
    "youtube": "youtube.com"
  },
  "Features": [
    {
      "icon": "fa fa-comments-o",
      "title": "Lorem ipsum",
      "text": "Lorem ipsum dolor sit amet placerat facilisis felis mi in tempus eleifend pellentesque natoque etiam."
    },
    {
      "icon": "fa fa-bullhorn",
      "title": "Lorem ipsum",
      "text": "Lorem ipsum dolor sit amet placerat facilisis felis mi in tempus eleifend pellentesque natoque etiam."
    },
    {
      "icon": "fa fa-group",
      "title": "Lorem ipsum",
      "text": "Lorem ipsum dolor sit amet placerat facilisis felis mi in tempus eleifend pellentesque natoque etiam."
    },
    {
      "icon": "fa fa-magic",
      "title": "Lorem ipsum",
      "text": "Lorem ipsum dolor sit amet placerat facilisis felis mi in tempus eleifend pellentesque natoque etiam."
    }
  ]
}
